{
  "parent": "skyrimcraft:shout/root",
  "criteria": {
    "spell_learned_dragon_aspect": {
      "conditions": {
        "skill": "skyrimcraft:dragon_aspect"
      },
      "trigger": "skyrimcraft:learn_spell"
    }
  },
  "display": {
    "description": "Learn the Dragon Aspect shout",
    "frame": "challenge",
    "hidden": true,
    "icon": {
      "count": 1,
      "id": "skyrimcraft:shout_block"
    },
    "title": "Dragon Aspect"
  },
  "requirements": [
    [
      "spell_learned_dragon_aspect"
    ]
  ],
  "sends_telemetry_event": true
}